xivapyi/__init__.py
xivapyi/client.py
xivapyi/errors.py
xivapyi/py.typed
xivapyi-0.1.0.dist-info/LICENSE
xivapyi-0.1.0.dist-info/WHEEL
xivapyi-0.1.0.dist-info/METADATA
xivapyi-0.1.0.dist-info/RECORD
