Metadata-Version: 2.1
Name: xivapyi
Version: 0.1.0
Summary: An async python3 wrapper around the XIVAPI for Final Fantasy XIV.
Home-page: https://github.com/Jonxslays/xivapyi
License: BSD-3-Clause
Author: Jonxslays
Requires-Python: >=3.6,<=3.10
Classifier: Development Status :: 1 - Planning
Classifier: Framework :: AsyncIO
Classifier: Framework :: aiohttp
Classifier: Intended Audience :: Developers
Classifier: License :: OSI Approved :: BSD License
Classifier: Natural Language :: English
Classifier: Operating System :: OS Independent
Classifier: Programming Language :: Python :: 3
Classifier: Programming Language :: Python :: 3 :: Only
Classifier: Programming Language :: Python :: 3.10
Classifier: Programming Language :: Python :: 3.6
Classifier: Programming Language :: Python :: 3.7
Classifier: Programming Language :: Python :: 3.8
Classifier: Programming Language :: Python :: 3.9
Classifier: Topic :: Games/Entertainment :: Role-Playing
Classifier: Topic :: Software Development :: Libraries :: Python Modules
Classifier: Typing :: Typed
Requires-Dist: aiohttp (>=3.7.4.post0,<4.0.0)
Project-URL: Repository, https://github.com/Jonxslays/xivapyi
